semiauto_classification/__init__.py
semiauto_classification/custom_transformers.py
semiauto_classification/pipeline_utils.py
semiauto_classification/utils.py
semiauto_classification/data/__init__.py
semiauto_classification/data/data_cleaning.py
semiauto_classification/data/data_ingestion.py
semiauto_classification/data/data_preprocessing.py
semiauto_classification/features/__init__.py
semiauto_classification/features/feature_engineering.py
semiauto_classification/logger/__init__.py
semiauto_classification/model/__init__.py
semiauto_classification/model/model_building.py
semiauto_classification/model/model_evaluation.py
semiauto_classification/model/model_optimization.py
semiauto_classification/visualization/__init__.py
semiauto_classification/visualization/projectflow_report.py
semiauto_classification-1.0.4.dist-info/LICENSE
semiauto_classification-1.0.4.dist-info/METADATA
semiauto_classification-1.0.4.dist-info/WHEEL
semiauto_classification-1.0.4.dist-info/entry_points.txt
semiauto_classification-1.0.4.dist-info/top_level.txt
semiauto_classification-1.0.4.dist-info/RECORD
